{"blogid": "123508532", "writerAge": "码龄5年", "writerBlogNum": "12", "writerCollect": "204", "writerComment": "26", "writerFan": "44", "writerGrade": "2级", "writerIntegral": "333", "writerName": "Wxy1122.", "writerProfileAdress": "..\\..\\static\\writer_image\\profile_123508532.jpg", "writerRankTotal": "112363", "writerRankWeekly": "218225", "writerThumb": "52", "writerVisitNum": "31498", "blog_read_count": "14011", "blog_time": "于 2022-03-15 19:53:52 发布", "blog_title": "IntelliJ IDEA中配置Tomcat（超详细）", "content": "<div class=\"article_content clearfix\" id=\"article_content\">\n<link href=\"../../static/bootstrap/css/csdnstyle.css\" rel=\"stylesheet\"/>\n<div class=\"markdown_views prism-tomorrow-night-eighties\" id=\"content_views\">\n<svg style=\"display: none;\" xmlns=\"http://www.w3.org/2000/svg\">\n<path d=\"M5,0 0,2.5 5,5z\" id=\"raphael-marker-block\" stroke-linecap=\"round\" style=\"-webkit-tap-highlight-color: rgba(0, 0, 0, 0);\"></path>\n</svg>\n<h1><a id=\"IntelliJ_IDEATomcat_0\"></a>在IntelliJ IDEA中配置Tomcat</h1>\n<h3><a id=\"Tomcat_1\"></a>一、下载及安装Tomcat</h3>\n<ol><li>首先进入Tomcat官网：<a href=\"http://tomcat.apache.org/\">http://tomcat.apache.org/</a>，在Download中选择需要下载的版本，然后根据电脑系统选择64位/32位的zip，开始下载（要记住安装路径！）。<br/> ps:有zip和exe两种格式的，zip（64-bit Windows zip(pgp,md5,sha1)）是免安装版的，exe（32-bit/64-bit Windows Service installer(pgp,md5,sha1)）是安装版。<br/> <img alt=\"在这里插入图片描述\" src=\"..\\..\\static\\image\\015af380353f4e9eb9993396f9b0110c.png\"/></li><li>下载完成后直接解压即可。<br/> <img alt=\"在这里插入图片描述\" src=\"..\\..\\static\\image\\c72397b731a54edc88e4d31b953a5b92.png\"/><br/> <img alt=\"在这里插入图片描述\" src=\"..\\..\\static\\image\\8a05b64e744f4d1bae3464dcb961feec.png\"/></li><li>在bin目录下找到startup.bat，点击启动Tomcat；<br/> bin下的startup.bat，点击启动Tomcat；<br/> <img alt=\"在这里插入图片描述\" src=\"..\\..\\static\\image\\59e4c0861fb0424d9077cd989e889e9d.png\"/><br/> 启动Tomcat后，打开浏览器，地址栏输入： http://localhost:8080 若出现如下页面则表示安装成功：<br/> <img alt=\"在这里插入图片描述\" src=\"..\\..\\static\\image\\20845be6081f4d3eaaaac408226ad334.png\"/></li></ol>\n<h3><a id=\"Tomcat_13\"></a>二、配置Tomcat环境变量</h3>\n<ol><li> <p>右击“我的电脑”，点击“属性”，选择\"高级系统设置\"，点击“环境变量”：<br/> <img alt=\"在这里插入图片描述\" src=\"..\\..\\static\\image\\b0a20a36afef424891abcee6f47def11.png\"/></p> </li><li> <p>在系统变量中新建CATALINA_BASE，CATALINA_HOME：<br/> 变量名分别为CATALINA_BASE和CATALINA_HOME，变量值为Tomcat的安装目录。<br/> <img alt=\"在这里插入图片描述\" src=\"..\\..\\static\\image\\62cfd4a4373949ae9091d7296b182137.png\"/><br/> <img alt=\"在这里插入图片描述\" src=\"..\\..\\static\\image\\496347ed240a497194bb7f12b43b7fa5.png\"/></p> </li><li> <p>在ClassPath和Path中添加变量值：<br/> （1） 在ClassPath的变量值中加入：%CATALINA_HOME%\\lib\\servlet-api.jar;<br/> PS：在变量值最后需要加英文状态下的“;”<br/> <img alt=\"在这里插入图片描述\" src=\"..\\..\\static\\image\\fe8a412b44494ff097d45837a334b40f.png\"/><br/> （2）在Path的变量值中加入：%CATALINA_HOME%\\bin和%CATALINA_HOME%\\lib：<br/> <img alt=\"在这里插入图片描述\" src=\"..\\..\\static\\image\\8790679c2da840aba7ace1cf8bc4d43a.png\"/><br/> 完成后点击确定，Tomcat环境变量就配置完成啦~</p> </li><li> <p>测试是否配置成功：<br/> 打开\"cmd\"/快捷键win+R，输入: startup，如果出现以下信息，说明环境变量配置成功：<br/> <img alt=\"在这里插入图片描述\" src=\"..\\..\\static\\image\\709eb6d74bcc4b9a9b4019ce053bf739.png\"/></p> </li></ol>\n<h3><a id=\"IntelliJ_IDEATomcat_31\"></a>三、在IntelliJ IDEA中配置Tomcat</h3>\n<ol><li>在File中选择Settings，然后在“Build,Execution,Deployment”中选择“Application Servers”，点击“+”，就可以看到Tomcat Server了。<br/> <img alt=\"在这里插入图片描述\" src=\"..\\..\\static\\image\\63fd337e5fb54fb4a8fe5bd68f4206d1.png\"/><br/> <img alt=\"在这里插入图片描述\" src=\"..\\..\\static\\image\\b66b2603a4c04c5a96be375747396821.png\"/><br/> <img alt=\"在这里插入图片描述\" src=\"..\\..\\static\\image\\3a3212e4485e47f284428daef37c9d67.png\"/></li><li>地址选择Tomcat的安装路径即可，导入后点OK。（Tomcat10版本可能会无法成功安装）<br/> <img alt=\"在这里插入图片描述\" src=\"..\\..\\static\\image\\e3b72152164d479db11772af2c120d7e.png\"/><br/> <img alt=\"在这里插入图片描述\" src=\"..\\..\\static\\image\\0fd704c7816843388e7711f5da24d414.png\"/></li><li>在Run-中选择Edit Configurations…，在“+”中，就选择Tomcat Server，点击Local：<br/> <img alt=\"在这里插入图片描述\" src=\"..\\..\\static\\image\\17a9adf1e9f445c1ad0ba0e739fffe30.png\"/><br/> <img alt=\"在这里插入图片描述\" src=\"..\\..\\static\\image\\099f018fa690427184c32ceee7439211.png\"/></li><li>在Configuration中找到Tomcat地址，然后点击 OK 即可。<br/> <img alt=\"在这里插入图片描述\" src=\"..\\..\\static\\image\\e9ebc5575c61496f8264a140839ecc60.png\"/><br/> 到这一步，Tomcat就配置完成啦~</li></ol>\n</div>\n<link href=\"https://csdnimg.cn/release/blogv2/dist/mdeditor/css/editerView/markdown_views-22a2fefd3b.css\" rel=\"stylesheet\"/>\n<link href=\"https://csdnimg.cn/release/blogv2/dist/mdeditor/css/style-4f8fbf9108.css\" rel=\"stylesheet\"/>\n</div>", "first_tag": "Others", "cpp": 0, "csharp": 0, "python": 0, "javascript": 0, "java": 0, "sql": 0, "php": 0, "time": "2022-03-15 19:53:52", "summary": "在中配置一、下载及安装首先进入官网：，在中选择需要下载的版本，然后根据电脑系统选择位位的，开始下载要记住安装路径！。有和两种格式的，是免安装版的，是安装版。在这里插入图片描述下载完成后直接解压即可。在"}