{"blogid": "125437769", "writerAge": "码龄10年", "writerBlogNum": "6", "writerCollect": "37", "writerComment": "13", "writerFan": "9", "writerGrade": "2级", "writerIntegral": "286", "writerName": "ChanceLee1", "writerProfileAdress": "..\\..\\static\\writer_image\\profile_125437769.jpg", "writerRankTotal": "52789", "writerRankWeekly": "214684", "writerThumb": "10", "writerVisitNum": "44529", "blog_read_count": "2211", "blog_time": "于 2022-06-24 01:43:33 发布", "blog_title": "Java连接mysql数据库的详细教程（增查）", "content": "<div class=\"article_content clearfix\" id=\"article_content\">\n<link href=\"../../static/bootstrap/css/csdnstyle.css\" rel=\"stylesheet\"/>\n<div class=\"markdown_views prism-atom-one-light\" id=\"content_views\">\n<svg style=\"display: none;\" xmlns=\"http://www.w3.org/2000/svg\">\n<path d=\"M5,0 0,2.5 5,5z\" id=\"raphael-marker-block\" stroke-linecap=\"round\" style=\"-webkit-tap-highlight-color: rgba(0, 0, 0, 0);\"></path>\n</svg>\n<p></p>\n<div class=\"toc\">\n<h3>java连接mysql数据库【便于理解的jdbc】</h3>\n<ul><li><a href=\"#_1\">一、开发环境</a></li><li><a href=\"#_7\">二、创建数据表</a></li><li><ul><li><a href=\"#1_Navicat_8\">1. 用Navicat图形化创建</a></li><li><a href=\"#2__10\">2. 用命令行创建</a></li></ul>\n</li><li><a href=\"#java_13\">三、创建java工程</a></li><li><ul><li><a href=\"#1eclipseFir__14\">1.在eclipse中创建一个工程：Fir (工程名自拟)</a></li><li><a href=\"#2Firlibjar_17\">2.在Fir工程下，创建lib文件夹（存在jar驱动文件）</a></li><li><a href=\"#3mysqlmysqlconnectorjava5113binjar_22\">3.导入mysql驱动（mysql-connector-java-5.1.13-bin.jar）</a></li><li><a href=\"#4Build_Path_26\">4.载入Build Path，否则会出错。</a></li><li><a href=\"#5srcclass_29\">5.在src下创建一个包，包内创建一个class类</a></li><li><a href=\"#7_34\">7.讲解</a></li><li><ul><li><a href=\"#71_JavaMysql_35\">7.1 Java连接Mysql的代码如下：</a></li><li><a href=\"#72Mysql_62\">7.2Mysql执行查看语句</a></li><li><a href=\"#73Mysql_95\">7.3Mysql插入语句</a></li></ul>\n</li><li><a href=\"#8TestJDBCjava_125\">8.完整TestJDBC.java文件（查看）</a></li></ul>\n</li></ul>\n</div>\n<p></p>\n<h1><a id=\"_1\"></a>一、开发环境</h1>\n<p>jdk安装：<br/> eclipse安装使用：<br/> mysql安装教程：<a href=\"https://blog.csdn.net/xiang_qi_li/article/details/125402414?spm=1001.2014.3001.5502\">详细参考</a><br/> Navicat安装教程：<a href=\"\">参考</a></p>\n<h1><a id=\"_7\"></a>二、创建数据表</h1>\n<h2><a id=\"1_Navicat_8\"></a>1. 用Navicat图形化创建</h2>\n<p><img alt=\"在这里插入图片描述\" src=\"..\\..\\static\\image\\d40d469a7d4542baa72ff4e4ff83cbdf.png\"/></p>\n<h2><a id=\"2__10\"></a>2. 用命令行创建</h2>\n<p>忽略。</p>\n<h1><a id=\"java_13\"></a>三、创建java工程</h1>\n<h2><a id=\"1eclipseFir__14\"></a>1.在eclipse中创建一个工程：Fir (工程名自拟)</h2>\n<p><img alt=\"在这里插入图片描述\" src=\"..\\..\\static\\image\\a6004fc248a34e1eb696b87ad59cba67.png\"/></p>\n<h2><a id=\"2Firlibjar_17\"></a>2.在Fir工程下，创建lib文件夹（存在jar驱动文件）</h2>\n<p>鼠标右键点击Fir工程 ——&gt; New ——&gt;Folder、<br/> 文件夹命名为lib<br/> <img alt=\"在这里插入图片描述\" src=\"..\\..\\static\\image\\78eef7cbf9e74c749a5fb914e7684c69.png\"/></p>\n<h2><a id=\"3mysqlmysqlconnectorjava5113binjar_22\"></a>3.导入mysql驱动（mysql-connector-java-5.1.13-bin.jar）</h2>\n<p>把mysql-connector-java-5.1.13-bin.jar文件，复制到jdbc工程下的lib文件夹里。<br/> ps：如果下载不了jar文件，可以私信我，或直接百度也行<br/> <img alt=\"在这里插入图片描述\" src=\"..\\..\\static\\image\\6f760de7c08542f68cffc8731fb2fe80.png\"/></p>\n<h2><a id=\"4Build_Path_26\"></a>4.载入Build Path，否则会出错。</h2>\n<p>鼠标右键点击该驱动——&gt;Build Path——&gt;Add to Build Path</p>\n<h2><a id=\"5srcclass_29\"></a>5.在src下创建一个包，包内创建一个class类</h2>\n<p>鼠标右键点击src → New → package，包名自己任意取 如jdbc;<br/> 再在该包下创建一个class类，名字为:TestJDBC<br/> <img alt=\"在这里插入图片描述\" src=\"..\\..\\static\\image\\4eb2a5ebf3b34abebb0dc51e567c4741.png\"/></p>\n<h2><a id=\"7_34\"></a>7.讲解</h2>\n<h3><a id=\"71_JavaMysql_35\"></a>7.1 Java连接Mysql的代码如下：</h3>\n<pre><code class=\"prism language-java\"><span class=\"token keyword\">private</span> <span class=\"token keyword\">static</span> <span class=\"token class-name\">String</span> url <span class=\"token operator\">=</span> <span class=\"token string\">\"jdbc:mysql://localhost:3306/test\"</span><span class=\"token punctuation\">;</span> \n\n<span class=\"token keyword\">private</span> <span class=\"token keyword\">static</span> <span class=\"token class-name\">String</span> userName <span class=\"token operator\">=</span> <span class=\"token string\">\"root\"</span><span class=\"token punctuation\">;</span>\n\n<span class=\"token keyword\">private</span> <span class=\"token keyword\">static</span> <span class=\"token class-name\">String</span> password <span class=\"token operator\">=</span> <span class=\"token string\">\"root\"</span><span class=\"token punctuation\">;</span><span class=\"token comment\">//密码自己填写</span>\n\n<span class=\"token keyword\">public</span> <span class=\"token keyword\">static</span> <span class=\"token keyword\">void</span> <span class=\"token function\">main</span><span class=\"token punctuation\">(</span><span class=\"token class-name\">String</span><span class=\"token punctuation\">[</span><span class=\"token punctuation\">]</span> args<span class=\"token punctuation\">)</span> <span class=\"token punctuation\">{<!-- --></span>\n\n<span class=\"token class-name\">MysqlConnectTest</span> mysql<span class=\"token operator\">=</span> <span class=\"token keyword\">new</span> <span class=\"token class-name\">MysqlConnectTest</span><span class=\"token punctuation\">(</span><span class=\"token punctuation\">)</span><span class=\"token punctuation\">;</span>\n\n<span class=\"token class-name\">Connection</span> con <span class=\"token operator\">=</span> mysql<span class=\"token punctuation\">.</span><span class=\"token function\">getConnection</span><span class=\"token punctuation\">(</span><span class=\"token punctuation\">)</span><span class=\"token punctuation\">;</span>\n\n<span class=\"token keyword\">if</span><span class=\"token punctuation\">(</span>con<span class=\"token operator\">==</span><span class=\"token keyword\">null</span><span class=\"token punctuation\">)</span><span class=\"token punctuation\">{<!-- --></span>    \n\n            <span class=\"token class-name\">System</span><span class=\"token punctuation\">.</span>out<span class=\"token punctuation\">.</span><span class=\"token function\">println</span><span class=\"token punctuation\">(</span><span class=\"token string\">\"与mysql数据库连接失败！\"</span><span class=\"token punctuation\">)</span><span class=\"token punctuation\">;</span>    \n\n        <span class=\"token punctuation\">}</span><span class=\"token keyword\">else</span><span class=\"token punctuation\">{<!-- --></span>    \n\n            <span class=\"token class-name\">System</span><span class=\"token punctuation\">.</span>out<span class=\"token punctuation\">.</span><span class=\"token function\">println</span><span class=\"token punctuation\">(</span><span class=\"token string\">\"与mysql数据库连接成功！\"</span><span class=\"token punctuation\">)</span><span class=\"token punctuation\">;</span>    \n\n        <span class=\"token punctuation\">}</span>\n\n<span class=\"token punctuation\">}</span>\n</code></pre>\n<h3><a id=\"72Mysql_62\"></a>7.2Mysql执行查看语句</h3>\n<pre><code class=\"prism language-java\"><span class=\"token class-name\">Statement</span> sts <span class=\"token operator\">=</span> <span class=\"token keyword\">null</span><span class=\"token punctuation\">;</span>\n\n<span class=\"token class-name\">String</span> sql <span class=\"token operator\">=</span> <span class=\"token string\">\"select * from stu \"</span><span class=\"token punctuation\">;</span>\n\n<span class=\"token class-name\">ResultSet</span> resul <span class=\"token operator\">=</span> <span class=\"token keyword\">null</span><span class=\"token punctuation\">;</span>\n\n<span class=\"token keyword\">try</span> <span class=\"token punctuation\">{<!-- --></span>\n\nsts <span class=\"token operator\">=</span> <span class=\"token punctuation\">(</span><span class=\"token class-name\">Statement</span><span class=\"token punctuation\">)</span> con<span class=\"token punctuation\">.</span><span class=\"token function\">createStatement</span><span class=\"token punctuation\">(</span><span class=\"token punctuation\">)</span><span class=\"token punctuation\">;</span>\n\nresul <span class=\"token operator\">=</span> sts<span class=\"token punctuation\">.</span><span class=\"token function\">executeQuery</span><span class=\"token punctuation\">(</span>sql<span class=\"token punctuation\">)</span><span class=\"token punctuation\">;</span>\n\n<span class=\"token punctuation\">}</span> <span class=\"token keyword\">catch</span> <span class=\"token punctuation\">(</span><span class=\"token class-name\">SQLException</span> e<span class=\"token punctuation\">)</span> <span class=\"token punctuation\">{<!-- --></span>\n\ne<span class=\"token punctuation\">.</span><span class=\"token function\">printStackTrace</span><span class=\"token punctuation\">(</span><span class=\"token punctuation\">)</span><span class=\"token punctuation\">;</span>\n\n<span class=\"token punctuation\">}</span>\n\n<span class=\"token class-name\">System</span><span class=\"token punctuation\">.</span>out<span class=\"token punctuation\">.</span><span class=\"token function\">println</span><span class=\"token punctuation\">(</span><span class=\"token string\">\"查询的结果如下：\"</span><span class=\"token punctuation\">)</span><span class=\"token punctuation\">;</span>\n\n<span class=\"token keyword\">while</span><span class=\"token punctuation\">(</span>resul<span class=\"token punctuation\">.</span><span class=\"token function\">next</span><span class=\"token punctuation\">(</span><span class=\"token punctuation\">)</span><span class=\"token punctuation\">)</span><span class=\"token punctuation\">{<!-- --></span>\n<span class=\"token class-name\">System</span><span class=\"token punctuation\">.</span>out<span class=\"token punctuation\">.</span><span class=\"token function\">print</span><span class=\"token punctuation\">(</span><span class=\"token string\">\"[\"</span><span class=\"token punctuation\">)</span><span class=\"token punctuation\">;</span>\n<span class=\"token class-name\">System</span><span class=\"token punctuation\">.</span>out<span class=\"token punctuation\">.</span><span class=\"token function\">print</span><span class=\"token punctuation\">(</span> resultSet<span class=\"token punctuation\">.</span><span class=\"token function\">getInt</span><span class=\"token punctuation\">(</span><span class=\"token number\">1</span><span class=\"token punctuation\">)</span><span class=\"token operator\">+</span><span class=\"token string\">\"\\t\"</span><span class=\"token punctuation\">)</span><span class=\"token punctuation\">;</span> <span class=\"token comment\">//第一列 对应的字段</span>\n<span class=\"token comment\">// System.out.print( resultSet.getInt(\"id\")+\"\\t\");</span>\n<span class=\"token class-name\">System</span><span class=\"token punctuation\">.</span>out<span class=\"token punctuation\">.</span><span class=\"token function\">print</span><span class=\"token punctuation\">(</span> resultSet<span class=\"token punctuation\">.</span><span class=\"token function\">getString</span><span class=\"token punctuation\">(</span><span class=\"token string\">\"name\"</span><span class=\"token punctuation\">)</span><span class=\"token operator\">+</span><span class=\"token string\">\"\\t\"</span><span class=\"token punctuation\">)</span><span class=\"token punctuation\">;</span>\n<span class=\"token class-name\">System</span><span class=\"token punctuation\">.</span>out<span class=\"token punctuation\">.</span><span class=\"token function\">print</span><span class=\"token punctuation\">(</span> resultSet<span class=\"token punctuation\">.</span><span class=\"token function\">getString</span><span class=\"token punctuation\">(</span><span class=\"token string\">\"sex\"</span><span class=\"token punctuation\">)</span><span class=\"token operator\">+</span><span class=\"token string\">\"\\t\"</span><span class=\"token punctuation\">)</span><span class=\"token punctuation\">;</span>\n<span class=\"token class-name\">System</span><span class=\"token punctuation\">.</span>out<span class=\"token punctuation\">.</span><span class=\"token function\">println</span><span class=\"token punctuation\">(</span><span class=\"token string\">\"]\"</span><span class=\"token punctuation\">)</span><span class=\"token punctuation\">;</span>\n\n<span class=\"token punctuation\">}</span>\n</code></pre>\n<h3><a id=\"73Mysql_95\"></a>7.3Mysql插入语句</h3>\n<pre><code class=\"prism language-java\"><span class=\"token class-name\">String</span> sql <span class=\"token operator\">=</span> <span class=\"token string\">\"insert into stu values ('6','李白','女')\"</span><span class=\"token punctuation\">;</span>\n\n<span class=\"token keyword\">int</span> i <span class=\"token operator\">=</span> <span class=\"token number\">0</span><span class=\"token punctuation\">;</span>\n\n<span class=\"token keyword\">try</span> <span class=\"token punctuation\">{<!-- --></span>\n\nsts <span class=\"token operator\">=</span> <span class=\"token punctuation\">(</span><span class=\"token class-name\">Statement</span><span class=\"token punctuation\">)</span> con<span class=\"token punctuation\">.</span><span class=\"token function\">createStatement</span><span class=\"token punctuation\">(</span><span class=\"token punctuation\">)</span><span class=\"token punctuation\">;</span>\n\ni <span class=\"token operator\">=</span> sts<span class=\"token punctuation\">.</span><span class=\"token function\">executeUpdate</span><span class=\"token punctuation\">(</span>sql<span class=\"token punctuation\">)</span><span class=\"token punctuation\">;</span>\n\n<span class=\"token keyword\">if</span><span class=\"token punctuation\">(</span>i <span class=\"token operator\">==</span> <span class=\"token operator\">-</span><span class=\"token number\">1</span><span class=\"token punctuation\">)</span><span class=\"token punctuation\">{<!-- --></span>\n\n<span class=\"token class-name\">System</span><span class=\"token punctuation\">.</span>out<span class=\"token punctuation\">.</span><span class=\"token function\">println</span><span class=\"token punctuation\">(</span><span class=\"token string\">\"插入失敗\"</span><span class=\"token punctuation\">)</span><span class=\"token punctuation\">;</span>\n\n<span class=\"token punctuation\">}</span><span class=\"token keyword\">else</span><span class=\"token punctuation\">{<!-- --></span>\n\n<span class=\"token class-name\">System</span><span class=\"token punctuation\">.</span>out<span class=\"token punctuation\">.</span><span class=\"token function\">println</span><span class=\"token punctuation\">(</span><span class=\"token string\">\"插入成功\"</span><span class=\"token punctuation\">)</span><span class=\"token punctuation\">;</span>\n\n<span class=\"token punctuation\">}</span>\n \n<span class=\"token punctuation\">}</span> <span class=\"token keyword\">catch</span> <span class=\"token punctuation\">(</span><span class=\"token class-name\">SQLException</span> e<span class=\"token punctuation\">)</span> <span class=\"token punctuation\">{<!-- --></span>\n\ne<span class=\"token punctuation\">.</span><span class=\"token function\">printStackTrace</span><span class=\"token punctuation\">(</span><span class=\"token punctuation\">)</span><span class=\"token punctuation\">;</span>\n\n<span class=\"token punctuation\">}</span>\n</code></pre>\n<h2><a id=\"8TestJDBCjava_125\"></a>8.完整TestJDBC.java文件（查看）</h2>\n<pre><code class=\"prism language-java\"><span class=\"token keyword\">package</span> <span class=\"token namespace\">jdbc</span><span class=\"token punctuation\">;</span>\n\n<span class=\"token keyword\">import</span> <span class=\"token namespace\">java<span class=\"token punctuation\">.</span>sql<span class=\"token punctuation\">.</span></span><span class=\"token class-name\">Connection</span><span class=\"token punctuation\">;</span>\n<span class=\"token keyword\">import</span> <span class=\"token namespace\">java<span class=\"token punctuation\">.</span>sql<span class=\"token punctuation\">.</span></span><span class=\"token class-name\">Driver</span><span class=\"token punctuation\">;</span>\n<span class=\"token keyword\">import</span> <span class=\"token namespace\">java<span class=\"token punctuation\">.</span>sql<span class=\"token punctuation\">.</span></span><span class=\"token class-name\">DriverManager</span><span class=\"token punctuation\">;</span>\n<span class=\"token keyword\">import</span> <span class=\"token namespace\">java<span class=\"token punctuation\">.</span>sql<span class=\"token punctuation\">.</span></span><span class=\"token class-name\">PreparedStatement</span><span class=\"token punctuation\">;</span>\n<span class=\"token keyword\">import</span> <span class=\"token namespace\">java<span class=\"token punctuation\">.</span>sql<span class=\"token punctuation\">.</span></span><span class=\"token class-name\">ResultSet</span><span class=\"token punctuation\">;</span>\n<span class=\"token keyword\">import</span> <span class=\"token namespace\">java<span class=\"token punctuation\">.</span>sql<span class=\"token punctuation\">.</span></span><span class=\"token class-name\">SQLException</span><span class=\"token punctuation\">;</span>\n\n\n<span class=\"token keyword\">public</span> <span class=\"token keyword\">class</span> <span class=\"token class-name\">TestJDBC</span> <span class=\"token punctuation\">{<!-- --></span>\n\n\t<span class=\"token keyword\">public</span> <span class=\"token keyword\">static</span> <span class=\"token keyword\">void</span> <span class=\"token function\">main</span><span class=\"token punctuation\">(</span><span class=\"token class-name\">String</span><span class=\"token punctuation\">[</span><span class=\"token punctuation\">]</span> args<span class=\"token punctuation\">)</span> <span class=\"token punctuation\">{<!-- --></span>\n\t\t<span class=\"token comment\">// TODO Auto-generated method stub</span>\n\t\t<span class=\"token class-name\">Connection</span> conn <span class=\"token operator\">=</span> <span class=\"token keyword\">null</span><span class=\"token punctuation\">;</span>\n        <span class=\"token keyword\">try</span> <span class=\"token punctuation\">{<!-- --></span>\n            <span class=\"token comment\">//1.数据库连接的4个基本要素</span>\n            <span class=\"token comment\">//①JDBC URL用于标识一个被注册的驱动程序，驱动程序管理器通过这个URL选择正确的驱动程序，从而建立到数据库的连接；</span>\n            <span class=\"token comment\">//jdbc：表示URL中的协议</span>\n            <span class=\"token comment\">//mysql：子协议，用于标识mysql数据库驱动程序</span>\n            <span class=\"token comment\">//localhost:本机的IP地址</span>\n            <span class=\"token comment\">//3306：mysql 默认端口号 </span>\n            <span class=\"token comment\">//test：表示访问test数据库</span>\n            <span class=\"token class-name\">String</span> url <span class=\"token operator\">=</span> <span class=\"token string\">\"jdbc:mysql://localhost:3306/test\"</span><span class=\"token punctuation\">;</span>\n            \n            <span class=\"token comment\">//user:登录数据库的用户名</span>\n            <span class=\"token class-name\">String</span> user <span class=\"token operator\">=</span> <span class=\"token string\">\"root\"</span><span class=\"token punctuation\">;</span> <span class=\"token comment\">//自己的账号</span>\n            <span class=\"token comment\">//password:用户名对应的密码，这些都是自己之前设定的</span>\n            <span class=\"token class-name\">String</span> password <span class=\"token operator\">=</span> <span class=\"token string\">\"  \"</span><span class=\"token punctuation\">;</span> <span class=\"token comment\">//自己的密码</span>\n            <span class=\"token comment\">//mySql的驱动：com.mysql.jdbc.Driver</span>\n            <span class=\"token class-name\">String</span> driverName <span class=\"token operator\">=</span> <span class=\"token string\">\"com.mysql.jdbc.Driver\"</span><span class=\"token punctuation\">;</span>\n             \n            <span class=\"token comment\">//2.实例化Driver</span>\n            <span class=\"token class-name\">Class</span> clazz <span class=\"token operator\">=</span> <span class=\"token class-name\">Class</span><span class=\"token punctuation\">.</span><span class=\"token function\">forName</span><span class=\"token punctuation\">(</span>driverName<span class=\"token punctuation\">)</span><span class=\"token punctuation\">;</span>\n            <span class=\"token class-name\">Driver</span> driver <span class=\"token operator\">=</span> <span class=\"token punctuation\">(</span><span class=\"token class-name\">Driver</span><span class=\"token punctuation\">)</span> clazz<span class=\"token punctuation\">.</span><span class=\"token function\">newInstance</span><span class=\"token punctuation\">(</span><span class=\"token punctuation\">)</span><span class=\"token punctuation\">;</span>\n             \n            <span class=\"token comment\">//3.通过DriverManager来注册驱动</span>\n            <span class=\"token class-name\">DriverManager</span><span class=\"token punctuation\">.</span><span class=\"token function\">registerDriver</span><span class=\"token punctuation\">(</span>driver<span class=\"token punctuation\">)</span><span class=\"token punctuation\">;</span>\n            <span class=\"token comment\">//4.通过DriverManager的getConnection方法，获取Connection类的对象</span>\n            conn <span class=\"token operator\">=</span> <span class=\"token class-name\">DriverManager</span><span class=\"token punctuation\">.</span><span class=\"token function\">getConnection</span><span class=\"token punctuation\">(</span>url<span class=\"token punctuation\">,</span> user<span class=\"token punctuation\">,</span> password<span class=\"token punctuation\">)</span><span class=\"token punctuation\">;</span>\n            <span class=\"token comment\">//5.打印出conn对象</span>\n            <span class=\"token class-name\">System</span><span class=\"token punctuation\">.</span>out<span class=\"token punctuation\">.</span><span class=\"token function\">println</span><span class=\"token punctuation\">(</span>conn<span class=\"token punctuation\">)</span><span class=\"token punctuation\">;</span>\n            \n            <span class=\"token comment\">//获取statement对象</span>\n            <span class=\"token comment\">/*Statement statement = connection.createStatement();*/</span>\n            <span class=\"token class-name\">String</span> sql <span class=\"token operator\">=</span> <span class=\"token string\">\"select * from stu\"</span><span class=\"token punctuation\">;</span>\n            <span class=\"token class-name\">PreparedStatement</span> preparedStatement <span class=\"token operator\">=</span> conn<span class=\"token punctuation\">.</span><span class=\"token function\">prepareStatement</span><span class=\"token punctuation\">(</span>sql<span class=\"token punctuation\">)</span><span class=\"token punctuation\">;</span>\n            <span class=\"token comment\">//执行语句</span>\n            <span class=\"token comment\">/**/</span>\n            <span class=\"token class-name\">ResultSet</span> resultSet <span class=\"token operator\">=</span> preparedStatement<span class=\"token punctuation\">.</span><span class=\"token function\">executeQuery</span><span class=\"token punctuation\">(</span>sql<span class=\"token punctuation\">)</span><span class=\"token punctuation\">;</span>\n            <span class=\"token comment\">//返回地数据存储在result中</span>\n            \n            <span class=\"token keyword\">while</span> <span class=\"token punctuation\">(</span>resultSet<span class=\"token punctuation\">.</span><span class=\"token function\">next</span><span class=\"token punctuation\">(</span><span class=\"token punctuation\">)</span><span class=\"token punctuation\">)</span><span class=\"token punctuation\">{<!-- --></span>\n                <span class=\"token class-name\">System</span><span class=\"token punctuation\">.</span>out<span class=\"token punctuation\">.</span><span class=\"token function\">print</span><span class=\"token punctuation\">(</span><span class=\"token string\">\"[\"</span><span class=\"token punctuation\">)</span><span class=\"token punctuation\">;</span>\n                <span class=\"token class-name\">System</span><span class=\"token punctuation\">.</span>out<span class=\"token punctuation\">.</span><span class=\"token function\">print</span><span class=\"token punctuation\">(</span> resultSet<span class=\"token punctuation\">.</span><span class=\"token function\">getInt</span><span class=\"token punctuation\">(</span><span class=\"token number\">1</span><span class=\"token punctuation\">)</span><span class=\"token operator\">+</span><span class=\"token string\">\"\\t\"</span><span class=\"token punctuation\">)</span><span class=\"token punctuation\">;</span> <span class=\"token comment\">//第一列 对应的字段</span>\n<span class=\"token comment\">//                System.out.print( resultSet.getInt(\"id\")+\"\\t\");</span>\n                <span class=\"token class-name\">System</span><span class=\"token punctuation\">.</span>out<span class=\"token punctuation\">.</span><span class=\"token function\">print</span><span class=\"token punctuation\">(</span> resultSet<span class=\"token punctuation\">.</span><span class=\"token function\">getString</span><span class=\"token punctuation\">(</span><span class=\"token string\">\"name\"</span><span class=\"token punctuation\">)</span><span class=\"token operator\">+</span><span class=\"token string\">\"\\t\"</span><span class=\"token punctuation\">)</span><span class=\"token punctuation\">;</span>\n                <span class=\"token class-name\">System</span><span class=\"token punctuation\">.</span>out<span class=\"token punctuation\">.</span><span class=\"token function\">print</span><span class=\"token punctuation\">(</span> resultSet<span class=\"token punctuation\">.</span><span class=\"token function\">getString</span><span class=\"token punctuation\">(</span><span class=\"token string\">\"sex\"</span><span class=\"token punctuation\">)</span><span class=\"token operator\">+</span><span class=\"token string\">\"\\t\"</span><span class=\"token punctuation\">)</span><span class=\"token punctuation\">;</span>\n                <span class=\"token class-name\">System</span><span class=\"token punctuation\">.</span>out<span class=\"token punctuation\">.</span><span class=\"token function\">println</span><span class=\"token punctuation\">(</span><span class=\"token string\">\"]\"</span><span class=\"token punctuation\">)</span><span class=\"token punctuation\">;</span>\n            <span class=\"token punctuation\">}</span>\n            <span class=\"token keyword\">if</span> <span class=\"token punctuation\">(</span>resultSet <span class=\"token operator\">!=</span> <span class=\"token keyword\">null</span><span class=\"token punctuation\">)</span><span class=\"token punctuation\">{<!-- --></span>\n                resultSet<span class=\"token punctuation\">.</span><span class=\"token function\">close</span><span class=\"token punctuation\">(</span><span class=\"token punctuation\">)</span><span class=\"token punctuation\">;</span>\n            <span class=\"token punctuation\">}</span>\n            <span class=\"token keyword\">if</span><span class=\"token punctuation\">(</span>preparedStatement <span class=\"token operator\">!=</span> <span class=\"token keyword\">null</span><span class=\"token punctuation\">)</span><span class=\"token punctuation\">{<!-- --></span>\n                preparedStatement<span class=\"token punctuation\">.</span><span class=\"token function\">close</span><span class=\"token punctuation\">(</span><span class=\"token punctuation\">)</span><span class=\"token punctuation\">;</span>\n            <span class=\"token punctuation\">}</span>\n            \n            \n        <span class=\"token punctuation\">}</span> <span class=\"token keyword\">catch</span> <span class=\"token punctuation\">(</span><span class=\"token class-name\">Exception</span> e<span class=\"token punctuation\">)</span> <span class=\"token punctuation\">{<!-- --></span>\n            <span class=\"token comment\">// TODO Auto-generated catch block</span>\n            e<span class=\"token punctuation\">.</span><span class=\"token function\">printStackTrace</span><span class=\"token punctuation\">(</span><span class=\"token punctuation\">)</span><span class=\"token punctuation\">;</span>\n        <span class=\"token punctuation\">}</span> <span class=\"token keyword\">finally</span> <span class=\"token punctuation\">{<!-- --></span>\n            <span class=\"token keyword\">try</span> <span class=\"token punctuation\">{<!-- --></span>\n                <span class=\"token comment\">//当conn不为空时</span>\n                <span class=\"token keyword\">if</span><span class=\"token punctuation\">(</span>conn <span class=\"token operator\">!=</span> <span class=\"token keyword\">null</span><span class=\"token punctuation\">)</span> \n                    <span class=\"token comment\">//关闭conn资源</span>\n                    conn<span class=\"token punctuation\">.</span><span class=\"token function\">close</span><span class=\"token punctuation\">(</span><span class=\"token punctuation\">)</span><span class=\"token punctuation\">;</span>\n            <span class=\"token punctuation\">}</span> <span class=\"token keyword\">catch</span> <span class=\"token punctuation\">(</span><span class=\"token class-name\">SQLException</span> e<span class=\"token punctuation\">)</span> <span class=\"token punctuation\">{<!-- --></span>\n                <span class=\"token comment\">// TODO Auto-generated catch block</span>\n                e<span class=\"token punctuation\">.</span><span class=\"token function\">printStackTrace</span><span class=\"token punctuation\">(</span><span class=\"token punctuation\">)</span><span class=\"token punctuation\">;</span>\n            <span class=\"token punctuation\">}</span>\n        <span class=\"token punctuation\">}</span>\n\t\t\n\n\t<span class=\"token punctuation\">}</span>\n\n<span class=\"token punctuation\">}</span>\n\n</code></pre>\n<p>注：该方法并非连接MySQL的最佳方法，但是对于入门者，比较容易理解</p>\n<pre><code class=\"prism language-java\">注意：\n<span class=\"token number\">1.</span>要填上自己数据库账号，和 密码；\n<span class=\"token number\">2.</span>要创建test数据库；\n<span class=\"token number\">3.</span>要创建stu表；\n<span class=\"token number\">4.</span>stu表的属性 有 id <span class=\"token punctuation\">,</span>name<span class=\"token punctuation\">,</span> sex  \n 否则需要自己修改代码。\n</code></pre>\n<p>mysql驱动链接：<a href=\"https://download.csdn.net/download/xiang_qi_li/85754606\">mysql-connector-java-5.1.13.zip</a><br/> 代码资源：<a href=\"https://download.csdn.net/download/xiang_qi_li/85754606\">下载</a></p>\n</div>\n<link href=\"https://csdnimg.cn/release/blogv2/dist/mdeditor/css/editerView/markdown_views-22a2fefd3b.css\" rel=\"stylesheet\"/>\n<link href=\"https://csdnimg.cn/release/blogv2/dist/mdeditor/css/style-4f8fbf9108.css\" rel=\"stylesheet\"/>\n</div>", "first_tag": "SQL", "cpp": 0, "csharp": 0, "python": 0, "javascript": 0, "java": 1, "sql": 1, "php": 0, "time": "2022-06-24 01:43:33", "summary": "连接数据库便于理解的一、开发环境二、创建数据表用图形化创建用命令行创建三、创建工程在中创建一个工程：工程名自拟在工程下，创建文件夹存在驱动文件导入驱动载入，否则会出错。在下创建一个包，包内创建一个类讲"}