{"blogid": "125769806", "writerAge": "码龄11年", "writerBlogNum": "307", "writerCollect": "2639", "writerComment": "321", "writerFan": "6460", "writerGrade": "6级", "writerIntegral": "6557", "writerName": "Color Space", "writerProfileAdress": "..\\..\\static\\writer_image\\profile_125769806.jpg", "writerRankTotal": "2259", "writerRankWeekly": "1390", "writerThumb": "393", "writerVisitNum": "676769", "blog_read_count": "1134", "blog_time": "已于 2022-07-13 18:51:30 修改", "blog_title": "OpenCvSharp (C# OpenCV) 指针方法读取和修改图像像素值(附源码)", "content": "<div class=\"article_content clearfix\" id=\"article_content\">\n<link href=\"../../static/bootstrap/css/csdnstyle.css\" rel=\"stylesheet\"/>\n<div class=\"htmledit_views\" id=\"content_views\">\n<h1><strong>导读</strong></h1>\n<p>    本文主要介绍如何在OpenCvSharp4中使用指针方法读取和修改图像像素值。</p>\n<h1>详细介绍</h1>\n<p>      At方法读取图像像素值方法请参考下面文章，At方法速度较慢，建议使用指针方法。</p>\n<p><a href=\"https://colorspace.blog.csdn.net/article/details/117769269\" title=\"C#图像处理-OpenCVSharp教程(九) OpenCVSharp读取或修改图像像素值_Color Space的博客-CSDN博客_opencvsharp 获取像素\">C#图像处理-OpenCVSharp教程(九) OpenCVSharp读取或修改图像像素值_Color Space的博客-CSDN博客_opencvsharp 获取像素</a></p>\n<p>    【1】本文使用的测试图像：</p>\n<p class=\"img-center\"><img alt=\"\" height=\"767\" src=\"..\\..\\static\\image\\69adf05b922e4e8d8f7c8816d52fc4d1.png\" width=\"600\"/></p>\n<p>    【2】任务要求：先对图像做二值化，然后改变图像的背景颜色为RGB值254, 247, 197，颜色如下：</p>\n<p class=\"img-center\"><img alt=\"\" height=\"150\" src=\"..\\..\\static\\image\\f7e592a1f92e4a6094dd4858725af9bb.png\" width=\"333\"/></p>\n<p>     【3】详细步骤如下：</p>\n<p>        ① 原图转为灰度图，然后使用固定阈值二值化，得到二值图</p>\n<pre><code class=\"language-cs\">Mat img = Cv2.ImRead(\"test.png\");\nMat gray</code></pre>\n</div>\n</div>", "first_tag": "C#", "cpp": 0, "csharp": 1, "python": 0, "javascript": 0, "java": 0, "sql": 0, "php": 0, "time": "2022-07-13 18:51:30", "summary": "导读本文主要介绍如何在中使用指针方法读取和修改图像像素值。详细介绍方法读取图像像素值方法请参考下面文章，方法速度较慢，建议使用指针方法。图像处理教程九读取或修改图像像素值的博客博客获取像素图像处理教程"}